calc_ultra/.DS_Store
calc_ultra/__init__.py
calc_ultra/example.py
calc_ultra/main.py
calc_ultra/texts/__init__.py
calc_ultra/texts/derivacalc.txt
calc_ultra/texts/intecalc.txt
calc_ultra/texts/limcalc.txt
calc_ultra/texts/main_screen.txt
calc_ultra/texts/settings.txt
calc_ultra/texts/utils.txt
calc_ultra-1.3.9.dist-info/LICENSE
calc_ultra-1.3.9.dist-info/METADATA
calc_ultra-1.3.9.dist-info/WHEEL
calc_ultra-1.3.9.dist-info/top_level.txt
calc_ultra-1.3.9.dist-info/RECORD
