Metadata-Version: 2.1
Name: calc_ultra
Version: 1.3.9
Summary: A graphing calculator with a menu-based interface.
Author-email: Huatao <huatao.xue@outlook.com>
Maintainer-email: Huatao <huatao.xue@outlook.com>
License: MIT License
Project-URL: Homepage, https://github.com/sudoer-Huatao/calc_ultra
Project-URL: Issues, https://github.com/sudoer-Huatao/calc_ultra/issues
Keywords: calculus,calculator
Classifier: Programming Language :: Python :: 3
Classifier: License :: OSI Approved :: MIT License
Requires-Python: >=3.8
License-File: LICENSE
Requires-Dist: sympy >=1.12.1
Requires-Dist: numpy >=2.0.0
Requires-Dist: matplotlib >=3.9.0
Requires-Dist: rich >=13.7.1
Requires-Dist: scipy >=1.14.0
Requires-Dist: prompt-toolkit >=3.0.47
